AUTHORS
LICENSE
MANIFEST.in
README.txt
lgpl-3.0.txt
setup.py
kabaret/__init__.py
kabaret/__init__.pyc
kabaret.naming.egg-info/PKG-INFO
kabaret.naming.egg-info/SOURCES.txt
kabaret.naming.egg-info/dependency_links.txt
kabaret.naming.egg-info/namespace_packages.txt
kabaret.naming.egg-info/top_level.txt
kabaret/naming/__init__.py
kabaret/naming/__init__.pyc
kabaret/naming/path.py
kabaret/naming/path.pyc
kabaret/naming/examples/__init__.py
kabaret/naming/examples/example_01.py
kabaret/naming/fields/__init__.py
kabaret/naming/fields/__init__.pyc
kabaret/naming/fields/choice.py
kabaret/naming/fields/choice.pyc
kabaret/naming/fields/compound.py
kabaret/naming/fields/compound.pyc
kabaret/naming/fields/computed.py
kabaret/naming/fields/computed.pyc
kabaret/naming/fields/field.py
kabaret/naming/fields/field.pyc
kabaret/naming/fields/fixed.py
kabaret/naming/fields/fixed.pyc
kabaret/naming/fields/indexing.py
kabaret/naming/fields/indexing.pyc
kabaret/naming/fields/multiple.py
kabaret/naming/fields/multiple.pyc