Metadata-Version: 1.0
Name: kabaret.naming
Version: 0.1.0b1
Summary: File and Folder naming convention modeling and exploitation.
Home-page: http://packages.python.org/kabaret/naming.html
Author: Damien Coureau
Author-email: dee@dee909.com
License: UNKNOWN
Platform: UNKNOWN
Classifier: Development Status :: 2 - Pre-Alpha
Classifier: Topic :: Office/Business
Classifier: Intended Audience :: Developers
Classifier: Operating System :: OS Independent
Classifier: Programming Language :: Python :: 2.6
Classifier: Programming Language :: Python :: 2.7
Classifier: License :: OSI Approved :: GNU Lesser General Public License v3 or later (LGPLv3+)
